fiaduzai/__init__.py
fiaduzai/core.py
fiaduzai-0.2.2.dist-info/METADATA
fiaduzai-0.2.2.dist-info/WHEEL
fiaduzai-0.2.2.dist-info/top_level.txt
fiaduzai-0.2.2.dist-info/RECORD
